LICENSE
MANIFEST.in
README.md
setup.py
cppiniter/__init__.py
cppiniter/cppiniter.py
cppiniter.egg-info/PKG-INFO
cppiniter.egg-info/SOURCES.txt
cppiniter.egg-info/dependency_links.txt
cppiniter.egg-info/entry_points.txt
cppiniter.egg-info/requires.txt
cppiniter.egg-info/top_level.txt
cppiniter/files/.clang-format
cppiniter/files/.clang-tidy
cppiniter/files/.gitignore
cppiniter/files/.pre-commit-config.yaml
cppiniter/files/CMakeLists.txt
cppiniter/files/CMakeSettings.json
cppiniter/files/README.md
cppiniter/files/conanfile.py
cppiniter/files/example/CMakeLists.txt
cppiniter/files/example/main.cpp
cppiniter/files/src/CMakeLists.txt
cppiniter/files/src/main.cpp
cppiniter/files/src/version.h.in
cppiniter/files/src/project_name/export.h
cppiniter/files/src/project_name/project_name.cpp
cppiniter/files/src/project_name/project_name.h
cppiniter/files/src/project_name/version.h.in
cppiniter/files/test/CMakeLists.txt
cppiniter/files/test/main.cpp