Metadata-Version: 2.4
Name: cppiniter
Version: 1.1.23
Summary: C++项目脚手架
Home-page: https://github.com/xyz1001/cppiniter
Author: xyz1001
Author-email: zgzf1001@gmail.com
License: MIT
Keywords: c++ scaffolding
Classifier: License :: OSI Approved :: MIT License
Classifier: Programming Language :: Python :: 3
License-File: LICENSE
Requires-Dist: pystache
Requires-Dist: docopt
Requires-Dist: inquirer
Dynamic: author
Dynamic: author-email
Dynamic: classifier
Dynamic: description
Dynamic: home-page
Dynamic: keywords
Dynamic: license
Dynamic: license-file
Dynamic: requires-dist
Dynamic: summary
